GoogleNb/GoogleDrive.py
GoogleNb/GoogleSheet.py
GoogleNb/__init__.py
GoogleNb-0.0.3.dist-info/LICENSE
GoogleNb-0.0.3.dist-info/METADATA
GoogleNb-0.0.3.dist-info/WHEEL
GoogleNb-0.0.3.dist-info/top_level.txt
GoogleNb-0.0.3.dist-info/RECORD
